gsemgr/__init__.py
gsemgr/__main__.py
gsemgr/common.py
gsemgr/ftp_server.py
gsemgr/gse_commands.py
gsemgr/http_server.py
gsemgr/quickfs.py
gsemgr/smp.py
gsemgr/smp_commands.py
gsemgr/smp_exceptions.py
gsemgr/terminal.py
gsemgr/vfs.py
gsemgr-3.6.1.dist-info/METADATA
gsemgr-3.6.1.dist-info/WHEEL
gsemgr-3.6.1.dist-info/entry_points.txt
gsemgr-3.6.1.dist-info/licenses/LICENSE.md
gsemgr-3.6.1.dist-info/RECORD
