Metadata-Version: 2.4
Name: gsemgr
Version: 3.6.1
Summary: gsemgr tool to communicate with GSE device
Author-email: Bogdan Marinescu <bogdan@gsat.us>
License-File: LICENSE.md
Requires-Python: >=3.12
Requires-Dist: cbor2>=5.6.5
Requires-Dist: click>=8.1.8
Requires-Dist: crc>=7.0.0
Requires-Dist: flask>=3.1.0
Requires-Dist: gse-utils>=2.7.0
Requires-Dist: prettytable>=3.11.0
Requires-Dist: pyftpdlib>=2.0.1
Requires-Dist: python-minifier>=2.11.3
Requires-Dist: tqdm>=4.66.6
